{
  "tests": {
    "GRA-001": {
      "test_name": "GRA-001",
      "encoding_id": "SYM-001",
      "prc_profile": {
        "regime": "MIXED::CONSERVES_GRADIENT",
        "behavior": "mixed",
        "dominant_timeline": {
          "timeline_compact": "late_saturation_only",
          "confidence": 0.4318181818181818,
          "variants": {
            "late_saturation_only": 95,
            "early_instability_to_saturation_complex": 95,
            "oscillatory_early_deviation_then_saturation": 20,
            "oscillatory_early_deviation_only": 5,
            "oscillatory_early_instability_then_deviation": 5
          }
        },
        "robustness": {
          "homogeneous": false,
          "mixed_behavior": true,
          "numerically_stable": false
        },
        "pathologies": {
          "numeric_instability": false,
          "oscillatory": false,
          "collapse": false,
          "trivial": false,
          "degrading": false
        },
        "n_runs": 220,
        "n_valid": 0,
        "confidence": "low",
        "confidence_metadata": {
          "level": "low",
          "criteria": {
            "min_runs_high": 20,
            "min_runs_medium": 10,
            "max_cv_homogeneous": 0.5,
            "min_timeline_confidence": 0.7
          },
          "rationale": "n_valid=0 < 10"
        }
      },
      "diagnostic_signature": {
        "dynamic_signature": {
          "deviation_onset_median": 1.0,
          "instability_onset_median": 0.0,
          "oscillatory_fraction": 0.13636363636363635,
          "saturation_fraction": 0.9545454545454546,
          "collapse_fraction": 0.0
        },
        "timeline_distribution": {
          "dominant_timeline": "late_saturation_only",
          "timeline_confidence": 0.4318181818181818,
          "timeline_variants": {
            "late_saturation_only": 95,
            "early_instability_to_saturation_complex": 95,
            "oscillatory_early_deviation_then_saturation": 20,
            "oscillatory_early_deviation_only": 5,
            "oscillatory_early_instability_then_deviation": 5
          }
        },
        "run_dispersion": {
          "final_value_iqr_ratio": 3155000000.0,
          "cv_across_runs": 1.8178365766336475,
          "bimodal_detected": true
        },
        "thresholds_used": {
          "timeline_early": 0.2,
          "timeline_mid": 0.6,
          "timeline_late": 0.6,
          "instability_detection": "P90 * 10 (relative)",
          "oscillatory_threshold": "10% sign changes",
          "saturation_cv": "5%",
          "bimodal_iqr_ratio": "3.0"
        }
      },
      "instrumentation": {
        "metric_name": "density",
        "summary_metrics": {
          "final_value": {
            "median": 0.0,
            "q1": 0.0,
            "q3": 0.3155,
            "mean": 0.21057318181818183,
            "std": 0.38278763214900197
          },
          "initial_value": 0.0,
          "mean_value": 0.2096563455450023,
          "cv": 1.8178365766336475
        },
        "data_completeness": {
          "dynamic_events_present": true,
          "timeseries_present": true,
          "fallback_used": false
        },
        "computation_metadata": {
          "profiling_version": "6.1",
          "profiling_module": "profiling_common",
          "profiling_axis": "encoding",
          "timeline_architecture": "compositional_relative",
          "n_runs": 220,
          "n_valid": 0
        }
      }
    },
    "PAT-001": {
      "test_name": "PAT-001",
      "encoding_id": "SYM-001",
      "prc_profile": {
        "regime": "MIXED::OSCILLATORY_UNSTABLE",
        "behavior": "mixed",
        "dominant_timeline": {
          "timeline_compact": "late_saturation_only",
          "confidence": 0.45454545454545453,
          "variants": {
            "late_saturation_only": 100,
            "early_instability_to_saturation_complex": 30,
            "oscillatory_early_instability_to_saturation_complex": 59,
            "oscillatory_early_instability_then_saturation": 10,
            "oscillatory_early_deviation_then_saturation": 1,
            "oscillatory_mid_deviation_only": 10,
            "oscillatory_early_deviation_only": 5,
            "oscillatory_late_deviation_then_saturation": 3,
            "oscillatory_late_deviation_only": 2
          }
        },
        "robustness": {
          "homogeneous": false,
          "mixed_behavior": true,
          "numerically_stable": false
        },
        "pathologies": {
          "numeric_instability": false,
          "oscillatory": true,
          "collapse": false,
          "trivial": false,
          "degrading": false
        },
        "n_runs": 220,
        "n_valid": 0,
        "confidence": "low",
        "confidence_metadata": {
          "level": "low",
          "criteria": {
            "min_runs_high": 20,
            "min_runs_medium": 10,
            "max_cv_homogeneous": 0.5,
            "min_timeline_confidence": 0.7
          },
          "rationale": "n_valid=0 < 10"
        }
      },
      "diagnostic_signature": {
        "dynamic_signature": {
          "deviation_onset_median": 1.0,
          "instability_onset_median": 0.0,
          "oscillatory_fraction": 0.4090909090909091,
          "saturation_fraction": 0.9227272727272727,
          "collapse_fraction": 0.0
        },
        "timeline_distribution": {
          "dominant_timeline": "late_saturation_only",
          "timeline_confidence": 0.45454545454545453,
          "timeline_variants": {
            "late_saturation_only": 100,
            "early_instability_to_saturation_complex": 30,
            "oscillatory_early_instability_to_saturation_complex": 59,
            "oscillatory_early_instability_then_saturation": 10,
            "oscillatory_early_deviation_then_saturation": 1,
            "oscillatory_mid_deviation_only": 10,
            "oscillatory_early_deviation_only": 5,
            "oscillatory_late_deviation_then_saturation": 3,
            "oscillatory_late_deviation_only": 2
          }
        },
        "run_dispersion": {
          "final_value_iqr_ratio": 24.183673469387756,
          "cv_across_runs": 0.7539872769919889,
          "bimodal_detected": true
        },
        "thresholds_used": {
          "timeline_early": 0.2,
          "timeline_mid": 0.6,
          "timeline_late": 0.6,
          "instability_detection": "P90 * 10 (relative)",
          "oscillatory_threshold": "10% sign changes",
          "saturation_cv": "5%",
          "bimodal_iqr_ratio": "3.0"
        }
      },
      "instrumentation": {
        "metric_name": "diversity_simpson",
        "summary_metrics": {
          "final_value": {
            "median": 0.5762,
            "q1": 0.0392,
            "q3": 0.948,
            "mean": 0.5389849999999999,
            "std": 0.4063878325649258
          },
          "initial_value": 0.4486,
          "mean_value": 0.5430375508819538,
          "cv": 0.7539872769919889
        },
        "data_completeness": {
          "dynamic_events_present": true,
          "timeseries_present": true,
          "fallback_used": false
        },
        "computation_metadata": {
          "profiling_version": "6.1",
          "profiling_module": "profiling_common",
          "profiling_axis": "encoding",
          "timeline_architecture": "compositional_relative",
          "n_runs": 220,
          "n_valid": 0
        }
      }
    },
    "SPA-001": {
      "test_name": "SPA-001",
      "encoding_id": "SYM-001",
      "prc_profile": {
        "regime": "MIXED::CONSERVES_SPECTRUM",
        "behavior": "mixed",
        "dominant_timeline": {
          "timeline_compact": "early_instability_to_saturation_complex",
          "confidence": 0.45454545454545453,
          "variants": {
            "late_saturation_only": 60,
            "early_instability_to_saturation_complex": 100,
            "mid_instability_to_saturation_complex": 20,
            "oscillatory_early_deviation_only": 40
          }
        },
        "robustness": {
          "homogeneous": false,
          "mixed_behavior": true,
          "numerically_stable": false
        },
        "pathologies": {
          "numeric_instability": false,
          "oscillatory": false,
          "collapse": false,
          "trivial": false,
          "degrading": false
        },
        "n_runs": 220,
        "n_valid": 0,
        "confidence": "low",
        "confidence_metadata": {
          "level": "low",
          "criteria": {
            "min_runs_high": 20,
            "min_runs_medium": 10,
            "max_cv_homogeneous": 0.5,
            "min_timeline_confidence": 0.7
          },
          "rationale": "n_valid=0 < 10"
        }
      },
      "diagnostic_signature": {
        "dynamic_signature": {
          "deviation_onset_median": 1.0,
          "instability_onset_median": 0.0,
          "oscillatory_fraction": 0.18181818181818182,
          "saturation_fraction": 0.8181818181818182,
          "collapse_fraction": 0.0
        },
        "timeline_distribution": {
          "dominant_timeline": "early_instability_to_saturation_complex",
          "timeline_confidence": 0.45454545454545453,
          "timeline_variants": {
            "late_saturation_only": 60,
            "early_instability_to_saturation_complex": 100,
            "mid_instability_to_saturation_complex": 20,
            "oscillatory_early_deviation_only": 40
          }
        },
        "run_dispersion": {
          "final_value_iqr_ratio": 12.759853594062426,
          "cv_across_runs": 2.5170611422199394,
          "bimodal_detected": true
        },
        "thresholds_used": {
          "timeline_early": 0.2,
          "timeline_mid": 0.6,
          "timeline_late": 0.6,
          "instability_detection": "P90 * 10 (relative)",
          "oscillatory_threshold": "10% sign changes",
          "saturation_cv": "5%",
          "bimodal_iqr_ratio": "3.0"
        }
      },
      "instrumentation": {
        "metric_name": "gradient_magnitude",
        "summary_metrics": {
          "final_value": {
            "median": 0.0439065,
            "q1": 0.029507,
            "q3": 0.376505,
            "mean": 1157155948.2107081,
            "std": 2912632272.729842
          },
          "initial_value": 0.046317,
          "mean_value": 1138541267.674368,
          "cv": 2.5170611422199394
        },
        "data_completeness": {
          "dynamic_events_present": true,
          "timeseries_present": true,
          "fallback_used": false
        },
        "computation_metadata": {
          "profiling_version": "6.1",
          "profiling_module": "profiling_common",
          "profiling_axis": "encoding",
          "timeline_architecture": "compositional_relative",
          "n_runs": 220,
          "n_valid": 0
        }
      }
    },
    "SPE-001": {
      "test_name": "SPE-001",
      "encoding_id": "SYM-001",
      "prc_profile": {
        "regime": "MIXED::OSCILLATORY_UNSTABLE",
        "behavior": "mixed",
        "dominant_timeline": {
          "timeline_compact": "early_instability_to_saturation_complex",
          "confidence": 0.2818181818181818,
          "variants": {
            "early_instability_then_saturation": 30,
            "early_instability_to_saturation_complex": 62,
            "late_saturation_only": 20,
            "oscillatory_early_instability_to_saturation_complex": 34,
            "early_deviation_then_instability": 20,
            "early_instability_to_collapse_complex": 20,
            "oscillatory_early_deviation_then_saturation": 17,
            "oscillatory_early_instability_then_deviation": 17
          }
        },
        "robustness": {
          "homogeneous": false,
          "mixed_behavior": true,
          "numerically_stable": false
        },
        "pathologies": {
          "numeric_instability": false,
          "oscillatory": true,
          "collapse": false,
          "trivial": false,
          "degrading": false
        },
        "n_runs": 220,
        "n_valid": 0,
        "confidence": "low",
        "confidence_metadata": {
          "level": "low",
          "criteria": {
            "min_runs_high": 20,
            "min_runs_medium": 10,
            "max_cv_homogeneous": 0.5,
            "min_timeline_confidence": 0.7
          },
          "rationale": "n_valid=0 < 10"
        }
      },
      "diagnostic_signature": {
        "dynamic_signature": {
          "deviation_onset_median": 1.0,
          "instability_onset_median": 0.0,
          "oscillatory_fraction": 0.3090909090909091,
          "saturation_fraction": 0.8318181818181818,
          "collapse_fraction": 0.09090909090909091
        },
        "timeline_distribution": {
          "dominant_timeline": "early_instability_to_saturation_complex",
          "timeline_confidence": 0.2818181818181818,
          "timeline_variants": {
            "early_instability_then_saturation": 30,
            "early_instability_to_saturation_complex": 62,
            "late_saturation_only": 20,
            "oscillatory_early_instability_to_saturation_complex": 34,
            "early_deviation_then_instability": 20,
            "early_instability_to_collapse_complex": 20,
            "oscillatory_early_deviation_then_saturation": 17,
            "oscillatory_early_instability_then_deviation": 17
          }
        },
        "run_dispersion": {
          "final_value_iqr_ratio": 18.475043782837126,
          "cv_across_runs": 3.2046088125507315,
          "bimodal_detected": true
        },
        "thresholds_used": {
          "timeline_early": 0.2,
          "timeline_mid": 0.6,
          "timeline_late": 0.6,
          "instability_detection": "P90 * 10 (relative)",
          "oscillatory_threshold": "10% sign changes",
          "saturation_cv": "5%",
          "bimodal_iqr_ratio": "3.0"
        }
      },
      "instrumentation": {
        "metric_name": "eigenvalue_max",
        "summary_metrics": {
          "final_value": {
            "median": 0.9575,
            "q1": 0.0571,
            "q3": 1.054925,
            "mean": 2.8929869988852645e+42,
            "std": 9.270891631222412e+42
          },
          "initial_value": 1.1593,
          "mean_value": 3.6579648450362086e+40,
          "cv": 3.2046088125507315
        },
        "data_completeness": {
          "dynamic_events_present": true,
          "timeseries_present": true,
          "fallback_used": false
        },
        "computation_metadata": {
          "profiling_version": "6.1",
          "profiling_module": "profiling_common",
          "profiling_axis": "encoding",
          "timeline_architecture": "compositional_relative",
          "n_runs": 220,
          "n_valid": 0
        }
      }
    },
    "SPE-002": {
      "test_name": "SPE-002",
      "encoding_id": "SYM-001",
      "prc_profile": {
        "regime": "MIXED::OSCILLATORY_UNSTABLE",
        "behavior": "mixed",
        "dominant_timeline": {
          "timeline_compact": "early_instability_to_saturation_complex",
          "confidence": 0.2818181818181818,
          "variants": {
            "early_instability_then_saturation": 30,
            "early_instability_to_saturation_complex": 62,
            "late_saturation_only": 20,
            "oscillatory_early_instability_to_saturation_complex": 34,
            "early_deviation_then_instability": 20,
            "early_instability_to_collapse_complex": 20,
            "oscillatory_early_deviation_then_saturation": 17,
            "oscillatory_early_instability_then_deviation": 17
          }
        },
        "robustness": {
          "homogeneous": false,
          "mixed_behavior": true,
          "numerically_stable": false
        },
        "pathologies": {
          "numeric_instability": false,
          "oscillatory": true,
          "collapse": false,
          "trivial": false,
          "degrading": false
        },
        "n_runs": 220,
        "n_valid": 0,
        "confidence": "low",
        "confidence_metadata": {
          "level": "low",
          "criteria": {
            "min_runs_high": 20,
            "min_runs_medium": 10,
            "max_cv_homogeneous": 0.5,
            "min_timeline_confidence": 0.7
          },
          "rationale": "n_valid=0 < 10"
        }
      },
      "diagnostic_signature": {
        "dynamic_signature": {
          "deviation_onset_median": 1.0,
          "instability_onset_median": 0.0,
          "oscillatory_fraction": 0.3090909090909091,
          "saturation_fraction": 0.8318181818181818,
          "collapse_fraction": 0.09090909090909091
        },
        "timeline_distribution": {
          "dominant_timeline": "early_instability_to_saturation_complex",
          "timeline_confidence": 0.2818181818181818,
          "timeline_variants": {
            "early_instability_then_saturation": 30,
            "early_instability_to_saturation_complex": 62,
            "late_saturation_only": 20,
            "oscillatory_early_instability_to_saturation_complex": 34,
            "early_deviation_then_instability": 20,
            "early_instability_to_collapse_complex": 20,
            "oscillatory_early_deviation_then_saturation": 17,
            "oscillatory_early_instability_then_deviation": 17
          }
        },
        "run_dispersion": {
          "final_value_iqr_ratio": 18.475043782837126,
          "cv_across_runs": 3.2046088125507315,
          "bimodal_detected": true
        },
        "thresholds_used": {
          "timeline_early": 0.2,
          "timeline_mid": 0.6,
          "timeline_late": 0.6,
          "instability_detection": "P90 * 10 (relative)",
          "oscillatory_threshold": "10% sign changes",
          "saturation_cv": "5%",
          "bimodal_iqr_ratio": "3.0"
        }
      },
      "instrumentation": {
        "metric_name": "spectral_radius",
        "summary_metrics": {
          "final_value": {
            "median": 0.9575,
            "q1": 0.0571,
            "q3": 1.054925,
            "mean": 2.8929869988852645e+42,
            "std": 9.270891631222412e+42
          },
          "initial_value": 1.1593,
          "mean_value": 3.6579648450362086e+40,
          "cv": 3.2046088125507315
        },
        "data_completeness": {
          "dynamic_events_present": true,
          "timeseries_present": true,
          "fallback_used": false
        },
        "computation_metadata": {
          "profiling_version": "6.1",
          "profiling_module": "profiling_common",
          "profiling_axis": "encoding",
          "timeline_architecture": "compositional_relative",
          "n_runs": 220,
          "n_valid": 0
        }
      }
    },
    "SYM-001": {
      "test_name": "SYM-001",
      "encoding_id": "SYM-001",
      "prc_profile": {
        "regime": "MIXED::CONSERVES_SYMMETRY",
        "behavior": "mixed",
        "dominant_timeline": {
          "timeline_compact": "late_saturation_only",
          "confidence": 0.45454545454545453,
          "variants": {
            "late_saturation_only": 100,
            "early_instability_to_saturation_complex": 20,
            "early_instability_then_deviation": 20,
            "early_deviation_then_instability": 10,
            "early_instability_to_collapse_complex": 30,
            "early_deviation_then_saturation": 10,
            "oscillatory_early_instability_to_saturation_complex": 10,
            "oscillatory_early_deviation_then_saturation": 20
          }
        },
        "robustness": {
          "homogeneous": false,
          "mixed_behavior": true,
          "numerically_stable": false
        },
        "pathologies": {
          "numeric_instability": false,
          "oscillatory": false,
          "collapse": true,
          "trivial": false,
          "degrading": false
        },
        "n_runs": 220,
        "n_valid": 0,
        "confidence": "low",
        "confidence_metadata": {
          "level": "low",
          "criteria": {
            "min_runs_high": 20,
            "min_runs_medium": 10,
            "max_cv_homogeneous": 0.5,
            "min_timeline_confidence": 0.7
          },
          "rationale": "n_valid=0 < 10"
        }
      },
      "diagnostic_signature": {
        "dynamic_signature": {
          "deviation_onset_median": 1.0,
          "instability_onset_median": 0.0,
          "oscillatory_fraction": 0.13636363636363635,
          "saturation_fraction": 0.8636363636363636,
          "collapse_fraction": 0.13636363636363635
        },
        "timeline_distribution": {
          "dominant_timeline": "late_saturation_only",
          "timeline_confidence": 0.45454545454545453,
          "timeline_variants": {
            "late_saturation_only": 100,
            "early_instability_to_saturation_complex": 20,
            "early_instability_then_deviation": 20,
            "early_deviation_then_instability": 10,
            "early_instability_to_collapse_complex": 30,
            "early_deviation_then_saturation": 10,
            "oscillatory_early_instability_to_saturation_complex": 10,
            "oscillatory_early_deviation_then_saturation": 20
          }
        },
        "run_dispersion": {
          "final_value_iqr_ratio": 12684437499.999998,
          "cv_across_runs": 4.599185132913298,
          "bimodal_detected": true
        },
        "thresholds_used": {
          "timeline_early": 0.2,
          "timeline_mid": 0.6,
          "timeline_late": 0.6,
          "instability_detection": "P90 * 10 (relative)",
          "oscillatory_threshold": "10% sign changes",
          "saturation_cv": "5%",
          "bimodal_iqr_ratio": "3.0"
        }
      },
      "instrumentation": {
        "metric_name": "asymmetry_norm",
        "summary_metrics": {
          "final_value": {
            "median": 0.0,
            "q1": 0.0,
            "q3": 1.2684437499999999,
            "mean": 4.576781008662509e+42,
            "std": 2.1049463171640536e+43
          },
          "initial_value": 1.645974,
          "mean_value": 5.786995945563459e+40,
          "cv": 4.599185132913298
        },
        "data_completeness": {
          "dynamic_events_present": true,
          "timeseries_present": true,
          "fallback_used": false
        },
        "computation_metadata": {
          "profiling_version": "6.1",
          "profiling_module": "profiling_common",
          "profiling_axis": "encoding",
          "timeline_architecture": "compositional_relative",
          "n_runs": 220,
          "n_valid": 0
        }
      }
    },
    "TOP-001": {
      "test_name": "TOP-001",
      "encoding_id": "SYM-001",
      "prc_profile": {
        "regime": "MIXED::CONSERVES_TOPOLOGY",
        "behavior": "mixed",
        "dominant_timeline": {
          "timeline_compact": "late_saturation_only",
          "confidence": 0.5909090909090909,
          "variants": {
            "late_saturation_only": 130,
            "early_instability_to_saturation_complex": 45,
            "oscillatory_early_deviation_then_collapse": 10,
            "oscillatory_early_deviation_only": 26,
            "oscillatory_late_saturation_only": 4,
            "early_instability_then_saturation": 5
          }
        },
        "robustness": {
          "homogeneous": false,
          "mixed_behavior": true,
          "numerically_stable": false
        },
        "pathologies": {
          "numeric_instability": false,
          "oscillatory": false,
          "collapse": false,
          "trivial": false,
          "degrading": false
        },
        "n_runs": 220,
        "n_valid": 0,
        "confidence": "low",
        "confidence_metadata": {
          "level": "low",
          "criteria": {
            "min_runs_high": 20,
            "min_runs_medium": 10,
            "max_cv_homogeneous": 0.5,
            "min_timeline_confidence": 0.7
          },
          "rationale": "n_valid=0 < 10"
        }
      },
      "diagnostic_signature": {
        "dynamic_signature": {
          "deviation_onset_median": 1.0,
          "instability_onset_median": 0.0,
          "oscillatory_fraction": 0.18181818181818182,
          "saturation_fraction": 0.8363636363636363,
          "collapse_fraction": 0.045454545454545456
        },
        "timeline_distribution": {
          "dominant_timeline": "late_saturation_only",
          "timeline_confidence": 0.5909090909090909,
          "timeline_variants": {
            "late_saturation_only": 130,
            "early_instability_to_saturation_complex": 45,
            "oscillatory_early_deviation_then_collapse": 10,
            "oscillatory_early_deviation_only": 26,
            "oscillatory_late_saturation_only": 4,
            "early_instability_then_saturation": 5
          }
        },
        "run_dispersion": {
          "final_value_iqr_ratio": 3.4,
          "cv_across_runs": 0.7456128694948293,
          "bimodal_detected": true
        },
        "thresholds_used": {
          "timeline_early": 0.2,
          "timeline_mid": 0.6,
          "timeline_late": 0.6,
          "instability_detection": "P90 * 10 (relative)",
          "oscillatory_threshold": "10% sign changes",
          "saturation_cv": "5%",
          "bimodal_iqr_ratio": "3.0"
        }
      },
      "instrumentation": {
        "metric_name": "connected_components",
        "summary_metrics": {
          "final_value": {
            "median": 50.0,
            "q1": 50.0,
            "q3": 170.0,
            "mean": 97.87272727272727,
            "std": 72.97516502717758
          },
          "initial_value": 102.0,
          "mean_value": 99.0751922207146,
          "cv": 0.7456128694948293
        },
        "data_completeness": {
          "dynamic_events_present": true,
          "timeseries_present": true,
          "fallback_used": false
        },
        "computation_metadata": {
          "profiling_version": "6.1",
          "profiling_module": "profiling_common",
          "profiling_axis": "encoding",
          "timeline_architecture": "compositional_relative",
          "n_runs": 220,
          "n_valid": 0
        }
      }
    },
    "UNIV-001": {
      "test_name": "UNIV-001",
      "encoding_id": "SYM-001",
      "prc_profile": {
        "regime": "MIXED::CONSERVES_NORM",
        "behavior": "mixed",
        "dominant_timeline": {
          "timeline_compact": "early_instability_to_saturation_complex",
          "confidence": 0.4090909090909091,
          "variants": {
            "early_instability_then_saturation": 30,
            "early_instability_to_saturation_complex": 90,
            "early_deviation_then_instability": 20,
            "early_instability_to_collapse_complex": 40,
            "oscillatory_early_instability_to_saturation_complex": 30,
            "oscillatory_early_instability_then_deviation": 10
          }
        },
        "robustness": {
          "homogeneous": false,
          "mixed_behavior": true,
          "numerically_stable": false
        },
        "pathologies": {
          "numeric_instability": false,
          "oscillatory": false,
          "collapse": true,
          "trivial": false,
          "degrading": false
        },
        "n_runs": 220,
        "n_valid": 0,
        "confidence": "low",
        "confidence_metadata": {
          "level": "low",
          "criteria": {
            "min_runs_high": 20,
            "min_runs_medium": 10,
            "max_cv_homogeneous": 0.5,
            "min_timeline_confidence": 0.7
          },
          "rationale": "n_valid=0 < 10"
        }
      },
      "diagnostic_signature": {
        "dynamic_signature": {
          "deviation_onset_median": 1.0,
          "instability_onset_median": 0.0,
          "oscillatory_fraction": 0.18181818181818182,
          "saturation_fraction": 0.8636363636363636,
          "collapse_fraction": 0.18181818181818182
        },
        "timeline_distribution": {
          "dominant_timeline": "early_instability_to_saturation_complex",
          "timeline_confidence": 0.4090909090909091,
          "timeline_variants": {
            "early_instability_then_saturation": 30,
            "early_instability_to_saturation_complex": 90,
            "early_deviation_then_instability": 20,
            "early_instability_to_collapse_complex": 40,
            "oscillatory_early_instability_to_saturation_complex": 30,
            "oscillatory_early_instability_then_deviation": 10
          }
        },
        "run_dispersion": {
          "final_value_iqr_ratio": 41.84548825710754,
          "cv_across_runs": 3.1642826052608495,
          "bimodal_detected": true
        },
        "thresholds_used": {
          "timeline_early": 0.2,
          "timeline_mid": 0.6,
          "timeline_late": 0.6,
          "instability_detection": "P90 * 10 (relative)",
          "oscillatory_threshold": "10% sign changes",
          "saturation_cv": "5%",
          "bimodal_iqr_ratio": "3.0"
        }
      },
      "instrumentation": {
        "metric_name": "frobenius_norm",
        "summary_metrics": {
          "final_value": {
            "median": 1.02095,
            "q1": 0.1618,
            "q3": 6.7706,
            "mean": 1.7870838531449286e+43,
            "std": 5.654838350649032e+43
          },
          "initial_value": 7.2685,
          "mean_value": 2.2596333521218365e+41,
          "cv": 3.1642826052608495
        },
        "data_completeness": {
          "dynamic_events_present": true,
          "timeseries_present": true,
          "fallback_used": false
        },
        "computation_metadata": {
          "profiling_version": "6.1",
          "profiling_module": "profiling_common",
          "profiling_axis": "encoding",
          "timeline_architecture": "compositional_relative",
          "n_runs": 220,
          "n_valid": 0
        }
      }
    },
    "UNIV-002": {
      "test_name": "UNIV-002",
      "encoding_id": "SYM-001",
      "prc_profile": {
        "regime": "MIXED::OSCILLATORY_UNSTABLE",
        "behavior": "mixed",
        "dominant_timeline": {
          "timeline_compact": "early_instability_then_saturation",
          "confidence": 0.2727272727272727,
          "variants": {
            "early_instability_then_saturation": 60,
            "oscillatory_early_instability_to_saturation_complex": 60,
            "early_deviation_then_instability": 20,
            "early_instability_to_saturation_complex": 34,
            "early_instability_to_collapse_complex": 6,
            "oscillatory_early_instability_then_deviation": 40
          }
        },
        "robustness": {
          "homogeneous": false,
          "mixed_behavior": true,
          "numerically_stable": false
        },
        "pathologies": {
          "numeric_instability": false,
          "oscillatory": true,
          "collapse": false,
          "trivial": false,
          "degrading": false
        },
        "n_runs": 220,
        "n_valid": 0,
        "confidence": "low",
        "confidence_metadata": {
          "level": "low",
          "criteria": {
            "min_runs_high": 20,
            "min_runs_medium": 10,
            "max_cv_homogeneous": 0.5,
            "min_timeline_confidence": 0.7
          },
          "rationale": "n_valid=0 < 10"
        }
      },
      "diagnostic_signature": {
        "dynamic_signature": {
          "deviation_onset_median": 1.0,
          "instability_onset_median": 0.0,
          "oscillatory_fraction": 0.45454545454545453,
          "saturation_fraction": 0.7272727272727273,
          "collapse_fraction": 0.02727272727272727
        },
        "timeline_distribution": {
          "dominant_timeline": "early_instability_then_saturation",
          "timeline_confidence": 0.2727272727272727,
          "timeline_variants": {
            "early_instability_then_saturation": 60,
            "oscillatory_early_instability_to_saturation_complex": 60,
            "early_deviation_then_instability": 20,
            "early_instability_to_saturation_complex": 34,
            "early_instability_to_collapse_complex": 6,
            "oscillatory_early_instability_then_deviation": 40
          }
        },
        "run_dispersion": {
          "final_value_iqr_ratio": 125.98684210526316,
          "cv_across_runs": 3.162297107005506,
          "bimodal_detected": true
        },
        "thresholds_used": {
          "timeline_early": 0.2,
          "timeline_mid": 0.6,
          "timeline_late": 0.6,
          "instability_detection": "P90 * 10 (relative)",
          "oscillatory_threshold": "10% sign changes",
          "saturation_cv": "5%",
          "bimodal_iqr_ratio": "3.0"
        }
      },
      "instrumentation": {
        "metric_name": "trace_normalized",
        "summary_metrics": {
          "final_value": {
            "median": 0.0229,
            "q1": 0.0076,
            "q3": 0.9575,
            "mean": 2.4418035203360128e+42,
            "std": 7.721708208234433e+42
          },
          "initial_value": 1.0,
          "mean_value": 3.087477212761937e+40,
          "cv": 3.162297107005506
        },
        "data_completeness": {
          "dynamic_events_present": true,
          "timeseries_present": true,
          "fallback_used": false
        },
        "computation_metadata": {
          "profiling_version": "6.1",
          "profiling_module": "profiling_common",
          "profiling_axis": "encoding",
          "timeline_architecture": "compositional_relative",
          "n_runs": 220,
          "n_valid": 0
        }
      }
    }
  },
  "n_tests": 9,
  "n_total_runs": 1980
}